etl_ml/__init__.py
etl_ml/try_etl_labels.py
etl_ml/try_push_insert_data.py
etl_ml/conf/__init__.py
etl_ml/etl/__init__.py
etl_ml/etl/add_cli_code.py
etl_ml/etl/etl_dt.py
etl_ml/etl/etl_dt_origin.py
etl_ml/etl/etl_label.py
etl_ml/etl/etl_master.py
etl_ml/etl/etl_th.py
etl_ml/etl/etl_ts.py
etl_ml/etl/push_insert_hive.py
etl_ml/etl/send_ftp_server.py
etl_ml/etl/yx_black_mobile_match.py
etl_ml/feature/__init__.py
etl_ml/feature/dockerdeom.py
etl_ml/feature/ex_txt.py
etl_ml/feature/obj4yaml.py
etl_ml/ml/__init__.py
etl_ml/ml/dataStat.py
etl_ml/ml/item_cf.py
etl_ml/shell/__init__.py
etl_ml/shell/etl_gui.py
etl_ml/shell/etl_terminal.py
etl_ml/utils/__init__.py
etl_ml/utils/em_cli.py
etl_ml/utils/ftps_client.py
etl_ml/utils/ssh_Tunnel.py
etl_ml/utils/ssh_utils.py
etl_ml/utils/try_email.py
etl_ml-1.0.7.dist-info/DESCRIPTION.rst
etl_ml-1.0.7.dist-info/METADATA
etl_ml-1.0.7.dist-info/RECORD
etl_ml-1.0.7.dist-info/WHEEL
etl_ml-1.0.7.dist-info/metadata.json
etl_ml-1.0.7.dist-info/top_level.txt
